maithili_dsl/__init__.py
maithili_dsl/cli.py
maithili_dsl/transpiler/__init__.py
maithili_dsl/transpiler/linter.py
maithili_dsl/transpiler/mappings.py
maithili_dsl/transpiler/numeral.py
maithili_dsl/transpiler/transpile.py
python_maithili-0.1.0.dist-info/licenses/LICENSE
python_maithili-0.1.0.dist-info/METADATA
python_maithili-0.1.0.dist-info/WHEEL
python_maithili-0.1.0.dist-info/entry_points.txt
python_maithili-0.1.0.dist-info/top_level.txt
python_maithili-0.1.0.dist-info/RECORD
