Metadata-Version: 2.4
Name: python_maithili
Version: 0.1.0
Summary: Run Python code written in Maithili using Devanagari script
Author: Bishwas Jha
Author-email: Bishwas Jha <jha.bishwas@gmail.com>
License: MIT
Project-URL: Homepage, https://github.com/alphacrack/python-maithili-dsl
Requires-Python: >=3.6
License-File: LICENSE
Dynamic: author
Dynamic: license-file
Dynamic: requires-python
